kwhmeter/__init__.py
kwhmeter/common.py
kwhmeter/endesa.py
kwhmeter/eredes.py
kwhmeter/exception.py
kwhmeter/iberdrola.py
kwhmeter/pvpc.py
kwhmeter/EdistribucionAPI/Edistribucion.py
kwhmeter/EdistribucionAPI/__init__.py
kwhmeter/scripts/__init__.py
kwhmeter/scripts/cli.py
kwhmeter-0.1.4.dist-info/LICENSE
kwhmeter-0.1.4.dist-info/METADATA
kwhmeter-0.1.4.dist-info/WHEEL
kwhmeter-0.1.4.dist-info/entry_points.txt
kwhmeter-0.1.4.dist-info/top_level.txt
kwhmeter-0.1.4.dist-info/RECORD
