Metadata-Version: 2.1
Name: kwhmeter
Version: 0.1.4
Summary: Clientes para lectura de contadores electricos de distribuidoras españolas
Home-page: https://github.com/nachoplus/kwhmeter.git
Author: nachomas
Author-email: mas.ignacio@gmail.com
Classifier: Programming Language :: Python :: 3
Classifier: License :: OSI Approved :: MIT License
Classifier: Operating System :: OS Independent
Requires-Python: >=3.6
License-File: LICENSE
Requires-Dist: click==7.1.2
Requires-Dist: pyyaml
Requires-Dist: requests
Requires-Dist: workalendar
Requires-Dist: pandas
Requires-Dist: openpyxl
Requires-Dist: bs4
Requires-Dist: python-dateutil
Requires-Dist: pyjsparser
